shortGPT/__init__.py
shortGPT/api_utils/__init__.py
shortGPT/api_utils/eleven_api.py
shortGPT/api_utils/image_api.py
shortGPT/api_utils/pexels_api.py
shortGPT/audio/__init__.py
shortGPT/audio/audio_duration.py
shortGPT/audio/audio_utils.py
shortGPT/audio/edge_voice_module.py
shortGPT/audio/eleven_voice_module.py
shortGPT/audio/voice_module.py
shortGPT/config/__init__.py
shortGPT/config/api_db.py
shortGPT/config/asset_db.py
shortGPT/config/config.py
shortGPT/config/languages.py
shortGPT/config/path_utils.py
shortGPT/database/__init__.py
shortGPT/database/content_data_manager.py
shortGPT/database/content_database.py
shortGPT/database/db_document.py
shortGPT/editing_framework/__init__.py
shortGPT/editing_framework/core_editing_engine.py
shortGPT/editing_framework/editing_engine.py
shortGPT/editing_framework/rendering_logger.py
shortGPT/editing_framework/editing_steps/__init__.py
shortGPT/editing_framework/editing_steps/add_background_video.json
shortGPT/editing_framework/editing_steps/add_background_voiceover.json
shortGPT/editing_framework/editing_steps/add_voiceover.json
shortGPT/editing_framework/editing_steps/background_music.json
shortGPT/editing_framework/editing_steps/crop_1920x1080_to_short.json
shortGPT/editing_framework/editing_steps/extract_audio.json
shortGPT/editing_framework/editing_steps/insert_audio.json
shortGPT/editing_framework/editing_steps/make_caption.json
shortGPT/editing_framework/editing_steps/make_caption_arabic.json
shortGPT/editing_framework/editing_steps/make_caption_arabic_landscape.json
shortGPT/editing_framework/editing_steps/make_caption_landscape.json
shortGPT/editing_framework/editing_steps/show_reddit_image.json
shortGPT/editing_framework/editing_steps/show_top_image.json
shortGPT/editing_framework/editing_steps/show_watermark.json
shortGPT/editing_framework/editing_steps/subscribe_animation.json
shortGPT/editing_framework/flows/__init__.py
shortGPT/editing_framework/flows/build_reddit_image.json
shortGPT/editing_utils/__init__.py
shortgpt-0.1.31.dist-info/LICENSE
shortgpt-0.1.31.dist-info/METADATA
shortgpt-0.1.31.dist-info/WHEEL
shortgpt-0.1.31.dist-info/top_level.txt
shortgpt-0.1.31.dist-info/RECORD
