Metadata-Version: 2.1
Name: shortgpt
Version: 0.1.31
Summary: Automating video and short content creation with AI
Author: RayVentura
Author-email: 
Keywords: python,video,content creation,AI,automation,editing,voiceover synthesis,video captions,asset sourcing,tinyDB
Classifier: Development Status :: 5 - Production/Stable
Classifier: Intended Audience :: Developers
Classifier: Programming Language :: Python :: 3
Classifier: Operating System :: Unix
Classifier: Operating System :: MacOS :: MacOS X
Classifier: Operating System :: Microsoft :: Windows
License-File: LICENSE
Requires-Dist: ffmpeg
Requires-Dist: python-dotenv
Requires-Dist: openai
Requires-Dist: tiktoken
Requires-Dist: tinydb
Requires-Dist: tinymongo
Requires-Dist: proglog
Requires-Dist: yt-dlp
Requires-Dist: torch
Requires-Dist: whisper-timestamped
Requires-Dist: torchaudio
Requires-Dist: pillow (==9.0.0)
Requires-Dist: protobuf (==3.20.0)
Requires-Dist: edge-tts
Requires-Dist: moviepy (==1.0.3)
Requires-Dist: progress
Requires-Dist: questionary
